MANIFEST.in
README.md
setup.py
robomission/__init__.py
robomission/field_background.py
robomission/space_game.py
robomission/space_world.py
robomission.egg-info/PKG-INFO
robomission.egg-info/SOURCES.txt
robomission.egg-info/dependency_links.txt
robomission.egg-info/not-zip-safe
robomission.egg-info/requires.txt
robomission.egg-info/top_level.txt
robomission/static/index.js
robomission/static/media/asteroid.png
robomission/static/media/background-blue.png
robomission/static/media/background-green.177310c4.png
robomission/static/media/background-green.png
robomission/static/media/background-red.bfe8d1cf.png
robomission/static/media/background-red.png
robomission/static/media/background-space.png
robomission/static/media/background-yellow.8a3529bd.png
robomission/static/media/background-yellow.png
robomission/static/media/explosion.png
robomission/static/media/fi-slide.jpg
robomission/static/media/icon-diamond.svg
robomission/static/media/icon-energy.svg
robomission/static/media/icon-length.svg
robomission/static/media/menu-banner.png
robomission/static/media/neurons-tile.png
robomission/static/media/spaceship-in-spaceworld.png
robomission/static/media/speedometer.png
robomission/static/media/wormhole.png
robomission/static/media/wormhole2.png
robomission/static/media/wormhole3.png
robomission/static/media/wormhole4.png