Metadata-Version: 1.0
Name: robomission
Version: 0.0.3
Summary: Visualization components for RoboMission
Home-page: https://github.com/adaptive-learning/robomission
Author: Tomas Effenberger
Author-email: xeffenberger@gmail.com
License: MIT
Platform: UNKNOWN
